[{"ID":0.6863740492932411,"Task":"hello","Current_date":"Fri Jul 15 2022 10:54:31 GMT-0400 (Eastern Daylight Time)","Due_date":"7/16/2022"},{"ID":0.35986669399464244,"Task":"no","Current_date":"Fri Jul 15 2022 10:57:59 GMT-0400 (Eastern Daylight Time)","Due_date":"7/23/2022"},{"ID":0.8281634162819973,"Task":"hello","Current_date":"Fri Jul 15 2022 11:01:19 GMT-0400 (Eastern Daylight Time)","Due_date":"7/16/2022"},{"ID":0.9013061721711364,"Task":"hello","Current_date":"Fri Jul 15 2022 11:14:18 GMT-0400 (Eastern Daylight Time)","Due_date":"7/16/2022"},{"ID":0.004546917513343018,"Task":"hello","Current_date":"Fri Jul 15 2022 11:15:53 GMT-0400 (Eastern Daylight Time)","Due_date":"7/16/2022"},{"ID":0.704461069240367,"Task":"no","Current_date":"Fri Jul 15 2022 11:16:30 GMT-0400 (Eastern Daylight Time)","Due_date":"7/16/2022"}]